{
  "type": "FeatureCollection",
  "features": [
    {
      "type": "Feature",
      "properties": {
        "osm_id": 88028818,
        "osm_type": "way",
        "type": "farmland",
        "name": null,
        "wikidata_id": null,
        "bounding_box": [
          50.8591979,
          7.0968864,
          50.8616573,
          7.0988536
        ]
      },
      "geometry": {
        "type": "Polygon",
        "coordinates": [
          [
            [
              7.0979944,
              50.8593681
            ],
            [
              7.0978554,
              50.8591979
            ],
            [
              7.0978096,
              50.859264
            ],
            [
              7.0977044,
              50.8592714
            ],
            [
              7.0975692,
              50.8592374
            ],
            [
              7.097455,
              50.8595211
            ],
            [
              7.0968864,
              50.8615034
            ],
            [
              7.098098,
              50.8616087
            ],
            [
              7.0988331,
              50.8616573
            ],
            [
              7.0988536,
              50.8615002
            ],
            [
              7.0988532,
              50.8613335
            ],
            [
              7.0988282,
              50.8611864
            ],
            [
              7.0987926,
              50.8610104
            ],
            [
              7.0987265,
              50.8608441
            ],
            [
              7.0986504,
              50.8606508
            ],
            [
              7.0985762,
              50.8604499
            ],
            [
              7.0984122,
              50.8601391
            ],
            [
              7.0982745,
              50.8598675
            ],
            [
              7.0979944,
              50.8593681
            ]
          ]
        ]
      }
    },
    {
      "type": "Feature",
      "properties": {
        "osm_id": 88386122,
        "osm_type": "way",
        "type": "allotments",
        "name": null,
        "wikidata_id": null,
        "bounding_box": [
          50.8525355,
          7.0983817,
          50.8544171,
          7.1009324
        ]
      },
      "geometry": {
        "type": "Polygon",
        "coordinates": [
          [
            [
              7.0983817,
              50.8541355
            ],
            [
              7.09873,
              50.8542744
            ],
            [
              7.0996344,
              50.8544017
            ],
            [
              7.0998361,
              50.8544171
            ],
            [
              7.1002793,
              50.8537448
            ],
            [
              7.1006765,
              50.8531468
            ],
            [
              7.1009324,
              50.8528063
            ],
            [
              7.1008483,
              50.8527689
            ],
            [
              7.1003238,
              50.8525355
            ],
            [
              7.0999962,
              50.8528256
            ],
            [
              7.0998593,
              50.8530077
            ],
            [
              7.0993509,
              50.8531898
            ],
            [
              7.0991407,
              50.8530972
            ],
            [
              7.0987789,
              50.8529367
            ],
            [
              7.0986724,
              50.8530036
            ],
            [
              7.0985104,
              50.8532306
            ],
            [
              7.0984987,
              50.8533029
            ],
            [
              7.098497,
              50.8534169
            ],
            [
              7.0984836,
              50.8535557
            ],
            [
              7.0984582,
              50.8537873
            ],
            [
              7.0983817,
              50.8541355
            ]
          ]
        ]
      }
    },
    {
      "type": "Feature",
      "properties": {
        "osm_id": 103595741,
        "osm_type": "way",
        "type": "farmland",
        "name": null,
        "wikidata_id": null,
        "bounding_box": [
          50.8656948,
          7.0960091,
          50.8686777,
          7.0977804
        ]
      },
      "geometry": {
        "type": "Polygon",
        "coordinates": [
          [
            [
              7.0963094,
              50.8659947
            ],
            [
              7.0969762,
              50.8659675
            ],
            [
              7.097051,
              50.8656948
            ],
            [
              7.0977735,
              50.8656976
            ],
            [
              7.0977804,
              50.8670306
            ],
            [
              7.0974362,
              50.8674134
            ],
            [
              7.0971911,
              50.8678185
            ],
            [
              7.0969967,
              50.8681888
            ],
            [
              7.0968235,
              50.868606
            ],
            [
              7.0960091,
              50.8686777
            ],
            [
              7.0963094,
              50.8659947
            ]
          ]
        ]
      }
    },
    {
      "type": "Feature",
      "properties": {
        "osm_id": 103595749,
        "osm_type": "way",
        "type": "forest",
        "name": null,
        "wikidata_id": null,
        "bounding_box": [
          50.8595211,
          7.0964382,
          50.8635226,
          7.0986841
        ]
      },
      "geometry": {
        "type": "Polygon",
        "coordinates": [
          [
            [
              7.0966849,
              50.8614847
            ],
            [
              7.0964382,
              50.8633809
            ],
            [
              7.0969317,
              50.8634079
            ],
            [
              7.0986841,
              50.8635226
            ],
            [
              7.096921,
              50.8632861
            ],
            [
              7.0970175,
              50.8621281
            ],
            [
              7.0973716,
              50.8621348
            ],
            [
              7.0974252,
              50.8618437
            ],
            [
              7.0982084,
              50.861864
            ],
            [
              7.098098,
              50.8616087
            ],
            [
              7.0968864,
              50.8615034
            ],
            [
              7.097455,
              50.8595211
            ],
            [
              7.0974176,
              50.8595561
            ],
            [
              7.0967922,
              50.8609836
            ],
            [
              7.0966849,
              50.8614847
            ]
          ]
        ]
      }
    },
    {
      "type": "Feature",
      "properties": {
        "osm_id": 103595765,
        "osm_type": "way",
        "type": "forest",
        "name": null,
        "wikidata_id": null,
        "bounding_box": [
          50.8635163,
          7.0958733,
          50.868694,
          7.0986376
        ]
      },
      "geometry": {
        "type": "Polygon",
        "coordinates": [
          [
            [
              7.0977149,
              50.8649316
            ],
            [
              7.0964596,
              50.8648977
            ],
            [
              7.0963094,
              50.8659947
            ],
            [
              7.0960091,
              50.8686777
            ],
            [
              7.0958733,
              50.868694
            ],
            [
              7.0964274,
              50.8635163
            ],
            [
              7.0986376,
              50.8636517
            ],
            [
              7.0986337,
              50.8637815
            ],
            [
              7.096921,
              50.8636924
            ],
            [
              7.0969249,
              50.8639154
            ],
            [
              7.0968884,
              50.8644576
            ],
            [
              7.0968244,
              50.864742
            ],
            [
              7.0977089,
              50.8647556
            ],
            [
              7.0977042,
              50.86483
            ],
            [
              7.0977149,
              50.8649316
            ]
          ]
        ]
      }
    },
    {
      "type": "Feature",
      "properties": {
        "osm_id": 133382241,
        "osm_type": "way",
        "type": "meadow",
        "name": null,
        "wikidata_id": null,
        "bounding_box": [
          50.8543659,
          7.1067579,
          50.8545586,
          7.1077374
        ]
      },
      "geometry": {
        "type": "Polygon",
        "coordinates": [
          [
            [
              7.1067579,
              50.8545241
            ],
            [
              7.1077286,
              50.8545586
            ],
            [
              7.1077374,
              50.854397
            ],
            [
              7.106772,
              50.8543659
            ],
            [
              7.1067579,
              50.8545241
            ]
          ]
        ]
      }
    },
    {
      "type": "Feature",
      "properties": {
        "osm_id": 261533253,
        "osm_type": "way",
        "type": "meadow",
        "name": null,
        "wikidata_id": null,
        "bounding_box": [
          50.8582015,
          7.103145,
          50.85839,
          7.1033755
        ]
      },
      "geometry": {
        "type": "Polygon",
        "coordinates": [
          [
            [
              7.103145,
              50.8583821
            ],
            [
              7.1032062,
              50.8583839
            ],
            [
              7.1033741,
              50.85839
            ],
            [
              7.1033755,
              50.8583521
            ],
            [
              7.1033715,
              50.8582463
            ],
            [
              7.1033684,
              50.8582015
            ],
            [
              7.1032043,
              50.8582361
            ],
            [
              7.1031519,
              50.8583569
            ],
            [
              7.103145,
              50.8583821
            ]
          ]
        ]
      }
    },
    {
      "type": "Feature",
      "properties": {
        "osm_id": 263949079,
        "osm_type": "way",
        "type": "forest",
        "name": null,
        "wikidata_id": null,
        "bounding_box": [
          50.8644678,
          7.1038677,
          50.8651158,
          7.1049941
        ]
      },
      "geometry": {
        "type": "Polygon",
        "coordinates": [
          [
            [
              7.1038914,
              50.8645457
            ],
            [
              7.1038677,
              50.8648379
            ],
            [
              7.1041637,
              50.8648445
            ],
            [
              7.1043715,
              50.8649869
            ],
            [
              7.104361,
              50.8651047
            ],
            [
              7.1046781,
              50.8651158
            ],
            [
              7.1049941,
              50.8648855
            ],
            [
              7.1047133,
              50.8647322
            ],
            [
              7.104486,
              50.8646277
            ],
            [
              7.1042112,
              50.8645176
            ],
            [
              7.104072,
              50.8644765
            ],
            [
              7.1040421,
              50.8644702
            ],
            [
              7.104001,
              50.8644678
            ],
            [
              7.1039711,
              50.8644718
            ],
            [
              7.1039213,
              50.8644906
            ],
            [
              7.1038926,
              50.864526
            ],
            [
              7.1038914,
              50.8645457
            ]
          ]
        ]
      }
    },
    {
      "type": "Feature",
      "properties": {
        "osm_id": 617577177,
        "osm_type": "way",
        "type": "meadow",
        "name": null,
        "wikidata_id": null,
        "bounding_box": [
          50.8584371,
          7.0971021,
          50.8586706,
          7.0975218
        ]
      },
      "geometry": {
        "type": "Polygon",
        "coordinates": [
          [
            [
              7.0971021,
              50.8586533
            ],
            [
              7.0971752,
              50.8586122
            ],
            [
              7.0972403,
              50.8585702
            ],
            [
              7.0973165,
              50.8585019
            ],
            [
              7.0973653,
              50.8584371
            ],
            [
              7.0973816,
              50.8584948
            ],
            [
              7.0974171,
              50.8585712
            ],
            [
              7.0974619,
              50.8586238
            ],
            [
              7.0975218,
              50.8586706
            ],
            [
              7.0971021,
              50.8586533
            ]
          ]
        ]
      }
    },
    {
      "type": "Feature",
      "properties": {
        "osm_id": 617577178,
        "osm_type": "way",
        "type": "meadow",
        "name": null,
        "wikidata_id": null,
        "bounding_box": [
          50.8589003,
          7.0971305,
          50.8591868,
          7.0977322
        ]
      },
      "geometry": {
        "type": "Polygon",
        "coordinates": [
          [
            [
              7.0971305,
              50.8589054
            ],
            [
              7.0971793,
              50.8589003
            ],
            [
              7.0976814,
              50.8589176
            ],
            [
              7.0977322,
              50.8589317
            ],
            [
              7.0976133,
              50.858994
            ],
            [
              7.0975269,
              50.8590665
            ],
            [
              7.097438,
              50.8591829
            ],
            [
              7.0974292,
              50.8591868
            ],
            [
              7.0974194,
              50.8591864
            ],
            [
              7.0974121,
              50.8591813
            ],
            [
              7.0973938,
              50.8591268
            ],
            [
              7.0973399,
              50.8590504
            ],
            [
              7.0972352,
              50.8589657
            ],
            [
              7.0971305,
              50.8589054
            ]
          ]
        ]
      }
    }
  ]
}